startpoint/__init__.py
startpoint/startpoint.py
startpoint/test.py
startpoint-1.3.4.dist-info/DESCRIPTION.rst
startpoint-1.3.4.dist-info/METADATA
startpoint-1.3.4.dist-info/RECORD
startpoint-1.3.4.dist-info/WHEEL
startpoint-1.3.4.dist-info/metadata.json
startpoint-1.3.4.dist-info/top_level.txt
