Metadata-Version: 1.0
Name: startpoint
Version: 1.3.4
Summary: A better entry point than if __name__ == '__main__'
Home-page: https://github.com/pavelbraginskiy/ismain/tree/master
Author: Pavel Braginskiy
Author-email: pavelbraginskiy@hotmail.com
License: MIT
Platform: UNKNOWN
